gpt_interface/__init__.py
gpt_interface/calls/call_gpt.py
gpt_interface/calls/legacy_model.py
gpt_interface/calls/modern_model.py
gpt_interface/calls/rate_limiter.py
gpt_interface/log/__init__.py
gpt_interface/log/pruning.py
gpt_interface/options/models.py
gpt_interface/options/system_message.py
gpt_interface/tools/__init__.py
gpt_interface/tools/functions.py
py_gpt_interface-0.8.2.dist-info/METADATA
py_gpt_interface-0.8.2.dist-info/WHEEL
py_gpt_interface-0.8.2.dist-info/licenses/LICENSE
py_gpt_interface-0.8.2.dist-info/RECORD
