Metadata-Version: 2.1
Name: py_gpt_interface
Version: 0.8.2
Summary: A simple interface for using the GPT API.
Author-Email: Matt Zhang <set.stun@gmail.com>
License: MIT
Project-URL: Homepage, https://github.com/MattUnderscoreZhang/gpt_interface
Requires-Python: >=3.8
Requires-Dist: openai>=1.2.4
Requires-Dist: tiktoken>=0.5.1
Requires-Dist: twine>=4.0.2
Requires-Dist: build>=1.0.3
Requires-Dist: python-dotenv>=1.0.0
Requires-Dist: pytest>=7.4.3
Requires-Dist: print-columns>=1.0.0
